ai/__init__.py
ippr/__init__.py
ippr-0.1.dist-info/METADATA
ippr-0.1.dist-info/WHEEL
ippr-0.1.dist-info/top_level.txt
ippr-0.1.dist-info/RECORD
