Metadata-Version: 2.1
Name: ippr
Version: 0.1
Summary: It contains all ipppr codes
Author: Shashank
